{
    "ship_1" : {
        "name": "Ship One",
        "class": 1,
        "layers" : [
            {
                "layer":0,
                "health":1000,
                "mass":1000
            }
        ],
        "comps": [
            {
                "layer":0,
                "id":"0001",
                "amt":4
            },
            {
                "layer":0,
                "id":"0100",
                "amt":1
            },
            {
                "layer":0,
                "id":"0200",
                "amt":1
            },
            {
                "layer":0,
                "id":"0300",
                "amt":1
            },
            {
                "layer":0,
                "id":"0400",
                "amt":1
            }
        ]
    }
}